winfiletime/__init__.py
winfiletime/filetime.py
winfiletime-2.1.dist-info/LICENSE
winfiletime-2.1.dist-info/METADATA
winfiletime-2.1.dist-info/WHEEL
winfiletime-2.1.dist-info/RECORD
