Metadata-Version: 2.3
Name: winfiletime
Version: 2.1
Summary: Win32 Filetime / Datetime conversion functions
License: CC0-1.0
Author: Jerome Leclanche
Author-email: jerome@leclan.ch
Requires-Python: >=3.7,<4.0
Classifier: Development Status :: 5 - Production/Stable
Classifier: Intended Audience :: Developers
Classifier: License :: CC0 1.0 Universal (CC0 1.0) Public Domain Dedication
Classifier: Programming Language :: Python :: 3
Classifier: Programming Language :: Python :: 3.7
Classifier: Programming Language :: Python :: 3.8
Classifier: Programming Language :: Python :: 3.9
Classifier: Programming Language :: Python :: 3.10
Classifier: Programming Language :: Python :: 3.11
Classifier: Programming Language :: Python :: 3.12
Classifier: Programming Language :: Python :: 3.13
Classifier: Topic :: System
Project-URL: Repository, https://github.com/jleclanche/winfiletime
